{
  "id": "",
  "name": "",
  "font_family": "iconfont",
  "css_prefix_text": "icon-",
  "description": "",
  "glyphs": [
    {
      "icon_id": "1039",
      "name": "钱袋",
      "font_class": "qiandai",
      "unicode": "f006e",
      "unicode_decimal": 983150
    },
    {
      "icon_id": "1041",
      "name": "平板电脑",
      "font_class": "pingbandiannao",
      "unicode": "f0070",
      "unicode_decimal": 983152
    },
    {
      "icon_id": "1305",
      "name": "购物车满",
      "font_class": "gouwucheman",
      "unicode": "f0178",
      "unicode_decimal": 983416
    },
    {
      "icon_id": "1306",
      "name": "购物车空",
      "font_class": "gouwuchekong",
      "unicode": "f0179",
      "unicode_decimal": 983417
    },
    {
      "icon_id": "5030",
      "name": "购物车满",
      "font_class": "gouwucheman1",
      "unicode": "344b",
      "unicode_decimal": 13387
    },
    {
      "icon_id": "202947",
      "name": "service-闪电退款",
      "font_class": "serviceshandiantuikuan",
      "unicode": "f023c",
      "unicode_decimal": 983612
    },
    {
      "icon_id": "227985",
      "name": "账户",
      "font_class": "sum",
      "unicode": "e947",
      "unicode_decimal": 59719
    },
    {
      "icon_id": "372265",
      "name": "cc-top",
      "font_class": "cc-top",
      "unicode": "e6a9",
      "unicode_decimal": 59049
    },
    {
      "icon_id": "436068",
      "name": "正品保证",
      "font_class": "2",
      "unicode": "e603",
      "unicode_decimal": 58883
    },
    {
      "icon_id": "515276",
      "name": "美元_dollars36",
      "font_class": "meiyuandollars36",
      "unicode": "e68f",
      "unicode_decimal": 59023
    },
    {
      "icon_id": "566023",
      "name": "电话",
      "font_class": "dianhua",
      "unicode": "e63e",
      "unicode_decimal": 58942
    },
    {
      "icon_id": "646367",
      "name": "钱袋",
      "font_class": "qiandai1",
      "unicode": "e628",
      "unicode_decimal": 58920
    },
    {
      "icon_id": "677589",
      "name": "密码",
      "font_class": "mima",
      "unicode": "e626",
      "unicode_decimal": 58918
    },
    {
      "icon_id": "749868",
      "name": "正品保障",
      "font_class": "zhengpinbz",
      "unicode": "e667",
      "unicode_decimal": 58983
    },
    {
      "icon_id": "859693",
      "name": "微信",
      "font_class": "weixin",
      "unicode": "e64f",
      "unicode_decimal": 58959
    },
    {
      "icon_id": "866294",
      "name": "美元_dollar155",
      "font_class": "meiyuandollar155",
      "unicode": "e953",
      "unicode_decimal": 59731
    },
    {
      "icon_id": "901941",
      "name": "耳机",
      "font_class": "erji",
      "unicode": "e608",
      "unicode_decimal": 58888
    },
    {
      "icon_id": "975275",
      "name": "咨询",
      "font_class": "zixun",
      "unicode": "e62c",
      "unicode_decimal": 58924
    },
    {
      "icon_id": "1009213",
      "name": "电话",
      "font_class": "dianhua1",
      "unicode": "e69a",
      "unicode_decimal": 59034
    },
    {
      "icon_id": "1221889",
      "name": "礼物",
      "font_class": "gift",
      "unicode": "e63c",
      "unicode_decimal": 58940
    },
    {
      "icon_id": "1306467",
      "name": "耳机",
      "font_class": "erji1",
      "unicode": "e614",
      "unicode_decimal": 58900
    },
    {
      "icon_id": "1311982",
      "name": "耳机",
      "font_class": "erji2",
      "unicode": "e63f",
      "unicode_decimal": 58943
    },
    {
      "icon_id": "1418223",
      "name": "上下",
      "font_class": "shangxia",
      "unicode": "e60b",
      "unicode_decimal": 58891
    },
    {
      "icon_id": "1917137",
      "name": "微信",
      "font_class": "wechat",
      "unicode": "e802",
      "unicode_decimal": 59394
    },
    {
      "icon_id": "2053441",
      "name": "pad 平板电脑",
      "font_class": "pad",
      "unicode": "e609",
      "unicode_decimal": 58889
    },
    {
      "icon_id": "2742683",
      "name": "游戏",
      "font_class": "youxi",
      "unicode": "e680",
      "unicode_decimal": 59008
    },
    {
      "icon_id": "3178272",
      "name": "电话",
      "font_class": "fl-dianhua",
      "unicode": "e63d",
      "unicode_decimal": 58941
    },
    {
      "icon_id": "4294027",
      "name": "电脑",
      "font_class": "diannao",
      "unicode": "e773",
      "unicode_decimal": 59251
    },
    {
      "icon_id": "4733970",
      "name": "游戏",
      "font_class": "youxi1",
      "unicode": "e622",
      "unicode_decimal": 58914
    },
    {
      "icon_id": "5387609",
      "name": "上下展开",
      "font_class": "shangxiazhankai",
      "unicode": "eb13",
      "unicode_decimal": 60179
    },
    {
      "icon_id": "5640058",
      "name": "搜索",
      "font_class": "sousuo",
      "unicode": "e627",
      "unicode_decimal": 58919
    },
    {
      "icon_id": "5650484",
      "name": "电脑",
      "font_class": "icon-test",
      "unicode": "e604",
      "unicode_decimal": 58884
    },
    {
      "icon_id": "5651479",
      "name": "个人",
      "font_class": "geren",
      "unicode": "e670",
      "unicode_decimal": 58992
    },
    {
      "icon_id": "6561240",
      "name": "咨询",
      "font_class": "zixun1",
      "unicode": "e625",
      "unicode_decimal": 58917
    },
    {
      "icon_id": "6929256",
      "name": "密码",
      "font_class": "mima1",
      "unicode": "e635",
      "unicode_decimal": 58933
    },
    {
      "icon_id": "7458947",
      "name": "上下移动箭头",
      "font_class": "shangxiayidongjiantou",
      "unicode": "e66a",
      "unicode_decimal": 58986
    },
    {
      "icon_id": "8371505",
      "name": "back top",
      "font_class": "backtop",
      "unicode": "e617",
      "unicode_decimal": 58903
    },
    {
      "icon_id": "11493434",
      "name": "搜索",
      "font_class": "sousuo1",
      "unicode": "e618",
      "unicode_decimal": 58904
    },
    {
      "icon_id": "12670569",
      "name": "礼物",
      "font_class": "liwu",
      "unicode": "e67c",
      "unicode_decimal": 59004
    },
    {
      "icon_id": "13769961",
      "name": "个人",
      "font_class": "geren1",
      "unicode": "e60c",
      "unicode_decimal": 58892
    },
    {
      "icon_id": "14055582",
      "name": "微信",
      "font_class": "weixin1",
      "unicode": "e61a",
      "unicode_decimal": 58906
    },
    {
      "icon_id": "15001662",
      "name": "咨询",
      "font_class": "zixun2",
      "unicode": "e664",
      "unicode_decimal": 58980
    }
  ]
}
